duckdb_extension_substrait/__init__.py
duckdb_extension_substrait/extensions/v1.1.3/substrait.duckdb_extension
duckdb_extension_substrait-1.1.3.dist-info/METADATA
duckdb_extension_substrait-1.1.3.dist-info/WHEEL
duckdb_extension_substrait-1.1.3.dist-info/RECORD
