Metadata-Version: 2.3
Name: duckdb_extension_substrait
Version: 1.1.3
Summary: Duckdb substrait extension
Project-URL: Documentation, https://github.com/santosh-d3vpl3x/duckdb_extensions#readme
Project-URL: Issues, https://github.com/santosh-d3vpl3x/duckdb_extensions/issues
Project-URL: Source, https://github.com/santosh-d3vpl3x/duckdb_extensions
Author-email: santosh <void@some.where>
License: MIT
Classifier: Development Status :: 4 - Beta
Classifier: License :: OSI Approved :: MIT License
Classifier: Programming Language :: Python
Classifier: Programming Language :: Python :: 3.8
Classifier: Programming Language :: Python :: 3.9
Classifier: Programming Language :: Python :: 3.10
Classifier: Programming Language :: Python :: 3.11
Classifier: Programming Language :: Python :: 3.12
Classifier: Programming Language :: Python :: 3.13
Classifier: Programming Language :: Python :: Implementation :: CPython
Classifier: Programming Language :: Python :: Implementation :: PyPy
Requires-Python: >=3.8
Requires-Dist: duckdb==1.1.3
Requires-Dist: importlib-resources==3.0.0; python_version < '3.9'
